elaspic2/__init__.py
elaspic2/__main__.py
elaspic2/elaspic2.py
elaspic2/types.py
elaspic2/utils.py
elaspic2/core/__init__.py
elaspic2/core/interface.py
elaspic2/core/utils.py
elaspic2/data/__init__.py
elaspic2/data/lgb/feature-columns-core.json
elaspic2/data/lgb/feature-columns-interface.json
elaspic2/data/lgb/lgb-model-core-0.txt
elaspic2/data/lgb/lgb-model-core-1.txt
elaspic2/data/lgb/lgb-model-core-2.txt
elaspic2/data/lgb/lgb-model-core-3.txt
elaspic2/data/lgb/lgb-model-core-4.txt
elaspic2/data/lgb/lgb-model-core-5.txt
elaspic2/data/lgb/lgb-model-interface-0.txt
elaspic2/data/lgb/lgb-model-interface-1.txt
elaspic2/data/lgb/lgb-model-interface-2.txt
elaspic2/data/lgb/lgb-model-interface-3.txt
elaspic2/data/lgb/lgb-model-interface-4.txt
elaspic2/data/lgb/lgb-model-interface-5.txt
elaspic2/data/pca/pca-columns-core.json
elaspic2/data/pca/pca-columns-interface.json
elaspic2/data/pca/pca-protbert_core2interface_features_protein_change-interface.pickle
elaspic2/data/pca/pca-protbert_core2interface_features_protein_wt-interface.pickle
elaspic2/data/pca/pca-protbert_core2interface_features_residue_change-interface.pickle
elaspic2/data/pca/pca-protbert_core2interface_features_residue_wt-interface.pickle
elaspic2/data/pca/pca-protbert_core_features_protein_change-core.pickle
elaspic2/data/pca/pca-protbert_core_features_protein_change-interface.pickle
elaspic2/data/pca/pca-protbert_core_features_protein_wt-core.pickle
elaspic2/data/pca/pca-protbert_core_features_protein_wt-interface.pickle
elaspic2/data/pca/pca-protbert_core_features_residue_change-core.pickle
elaspic2/data/pca/pca-protbert_core_features_residue_change-interface.pickle
elaspic2/data/pca/pca-protbert_core_features_residue_wt-core.pickle
elaspic2/data/pca/pca-protbert_core_features_residue_wt-interface.pickle
elaspic2/data/pca/pca-protbert_interface_features_protein_change-interface.pickle
elaspic2/data/pca/pca-protbert_interface_features_protein_wt-interface.pickle
elaspic2-0.1.7.dist-info/LICENSE
elaspic2-0.1.7.dist-info/METADATA
elaspic2-0.1.7.dist-info/WHEEL
elaspic2-0.1.7.dist-info/top_level.txt
elaspic2-0.1.7.dist-info/RECORD
