Metadata-Version: 2.1
Name: elaspic2
Version: 0.1.7
Summary: Predicting the effect of mutations on protein folding and protein-protein interaction.
Home-page: https://gitlab.com/elaspic/elaspic2
Author: Alexey Strokach
Author-email: alex.strokach@utoronto.ca
License: UNKNOWN
Keywords: elaspic2
Platform: UNKNOWN
Classifier: Development Status :: 2 - Pre-Alpha
Classifier: Intended Audience :: Developers
Classifier: Natural Language :: English
Classifier: Programming Language :: Python :: 3.7
Classifier: Programming Language :: Python :: 3.8
Requires-Dist: biopython (<2.0,>=1.78)
Requires-Dist: brotlipy (<0.8,>=0.7)
Requires-Dist: fire (<0.4,>=0.3)
Requires-Dist: mdtraj (<1.10,>=1.9)
Requires-Dist: mmtf-python (<1.2,>=1.1)
Requires-Dist: nglview (<2.8,>=2.7)
Requires-Dist: paramiko (<2.8,>=2.7)
Requires-Dist: tenacity (<6.3,>=6.2)
Requires-Dist: tqdm (<4.55,>=4.50)
